ankaflow/__init__.py
ankaflow/api.py
ankaflow/cli.py
ankaflow/const.py
ankaflow/errors.py
ankaflow/common/filesystem.py
ankaflow/common/path.py
ankaflow/common/renderer.py
ankaflow/common/types.py
ankaflow/common/util.py
ankaflow/connections/__init__.py
ankaflow/connections/bigquery.py
ankaflow/connections/clickhouse.py
ankaflow/connections/connection.py
ankaflow/connections/delta.py
ankaflow/connections/errors.py
ankaflow/connections/file.py
ankaflow/connections/llm/errors.py
ankaflow/connections/llm/protocols.py
ankaflow/connections/llm/sqlgen.py
ankaflow/connections/rest/browser.py
ankaflow/connections/rest/common.py
ankaflow/connections/rest/rest.py
ankaflow/connections/rest/server.py
ankaflow/core/__init__.py
ankaflow/core/flow.py
ankaflow/core/policy.py
ankaflow/internal/__init__.py
ankaflow/internal/browser.py
ankaflow/internal/duckdb.py
ankaflow/internal/errors.py
ankaflow/internal/macros.py
ankaflow/internal/server.py
ankaflow/models/__init__.py
ankaflow/models/components.py
ankaflow/models/configs.py
ankaflow/models/connections.py
ankaflow/models/core.py
ankaflow/models/enums.py
ankaflow/models/llm.py
ankaflow/models/rest.py
ankaflow-0.4.2.dist-info/METADATA
ankaflow-0.4.2.dist-info/WHEEL
ankaflow-0.4.2.dist-info/entry_points.txt
ankaflow-0.4.2.dist-info/top_level.txt
ankaflow-0.4.2.dist-info/RECORD
