Metadata-Version: 2.4
Name: ankaflow
Version: 0.4.2
Summary: Data pipeline (ETL) framework for server and browser
Author: Madis Udam
License: MIT
Requires-Python: >=3.12
Requires-Dist: duckdb<1.4.0,>=1.1.2
Requires-Dist: pandas>=2.2.3
Requires-Dist: pyarrow>=18.1.0
Requires-Dist: fsspec>=2024.3.1
Requires-Dist: pyyaml==6.0.2
Requires-Dist: typing-extensions==4.13.0
Requires-Dist: arrow==1.2.1
Requires-Dist: sqlglot==25.24.4
Requires-Dist: pydantic==2.10.6
Requires-Dist: jinja2==3.1.2
Requires-Dist: pypika-fork==0.49.0
Requires-Dist: shortuuid==1.0.13
Requires-Dist: jmespath==1.0.1
Requires-Dist: openpyxl==3.1.5
Provides-Extra: server
Requires-Dist: psutil>=7.0.0; extra == "server"
Requires-Dist: boto3==1.36.4; extra == "server"
Requires-Dist: clickhouse-driver==0.2.9; extra == "server"
Requires-Dist: google-cloud-storage==2.11.0; extra == "server"
Requires-Dist: httpx==0.21.1; extra == "server"
Requires-Dist: deltalake==0.25.4; extra == "server"
Requires-Dist: google-cloud-bigquery==3.26.0; extra == "server"
Requires-Dist: google-cloud-bigquery-storage==2.13.1; extra == "server"
Provides-Extra: browser
Requires-Dist: duckdb; extra == "browser"
Requires-Dist: pandas; extra == "browser"
Requires-Dist: fsspec; extra == "browser"
Requires-Dist: pyarrow; extra == "browser"
Provides-Extra: dev
Requires-Dist: black>=25.1.0; extra == "dev"
Requires-Dist: ruff>=0.9.4; extra == "dev"
Requires-Dist: build; extra == "dev"
Requires-Dist: mkdocs>=1.6.1; extra == "dev"
Requires-Dist: mkdocs-exclude>=1.0.2; extra == "dev"
Requires-Dist: mkdocs-material>=9.6.12; extra == "dev"
Requires-Dist: mkdocstrings>=0.29.1; extra == "dev"
Requires-Dist: mkdocs-autorefs>=1.4.1; extra == "dev"
Requires-Dist: mkdocstrings-python>=1.16.10; extra == "dev"
Requires-Dist: pyodide-py>=0.27.4; extra == "dev"
